filedial/__init__.py
filedial/_wip_.py
filedial/filedial.py
filedial-0.1.0.dist-info/WHEEL
filedial-0.1.0.dist-info/METADATA
filedial-0.1.0.dist-info/RECORD
